rilacs/__init__.py
rilacs/confseqs.py
rilacs/incremental_audit.py
rilacs/martingales.py
rilacs/misc.py
rilacs/plotting.py
rilacs/strategies.py
rilacs-1.0.3.dist-info/LICENSE
rilacs-1.0.3.dist-info/METADATA
rilacs-1.0.3.dist-info/WHEEL
rilacs-1.0.3.dist-info/top_level.txt
rilacs-1.0.3.dist-info/RECORD
